usepy_plugin_logger/__init__.py
usepy_plugin_logger/formatters.py
usepy_plugin_logger/handlers.py
usepy_plugin_logger/intercept.py
usepy_plugin_logger/logger.py
usepy_plugin_logger-0.1.6.dist-info/METADATA
usepy_plugin_logger-0.1.6.dist-info/WHEEL
usepy_plugin_logger-0.1.6.dist-info/RECORD
