Metadata-Version: 2.1
Name: usepy-plugin-logger
Version: 0.1.6
Summary: 一个全局拦截日志并转为loguru日志的插件
Author: nowanti
Author-email: believel.y@qq.com
Requires-Python: >=3.7,<4.0
Classifier: Programming Language :: Python :: 3
Classifier: Programming Language :: Python :: 3.7
Classifier: Programming Language :: Python :: 3.8
Classifier: Programming Language :: Python :: 3.9
Classifier: Programming Language :: Python :: 3.10
Classifier: Programming Language :: Python :: 3.11
Requires-Dist: loguru (>=0.6.0,<0.7.0)
